{"filters": {
    "benefits": [
        "water heater",
        "pineapple"
    ],
    "constraints": [
        "gas stove",
        "popcorn"
    ]
},
"types": {
    "wind": {
        "_score": 0,
        "water heater": true,
        "pineapple": false,
        "gas stove": false
    },
    "earthship": {
        "_score": 0,
        "water heater": false,
        "pineapple": false,
        "gas stove": true,
        "popcorn": true
    },
    "solar": {
        "_score": 0
    },
    "geothermal": {
        "_score": 0
    }
}
}